fika_analytics/__init__.py
fika_analytics/analytics_constants.py
fika_analytics/analytics_event.py
fika_analytics/fika_analytics.py
fika_analytics/user_property.py
fika_analytics_0.1.0-0.1.3.dist-info/DESCRIPTION.rst
fika_analytics_0.1.0-0.1.3.dist-info/METADATA
fika_analytics_0.1.0-0.1.3.dist-info/RECORD
fika_analytics_0.1.0-0.1.3.dist-info/WHEEL
fika_analytics_0.1.0-0.1.3.dist-info/metadata.json
fika_analytics_0.1.0-0.1.3.dist-info/top_level.txt
